macleod_ide/__init__.py
macleod_ide/spyder/__init__.py
macleod_ide/spyder/api.py
macleod_ide/spyder/confpage.py
macleod_ide/spyder/container.py
macleod_ide/spyder/plugin.py
macleod_ide/spyder/widgets.py
macleod_ide-0.0.2.dev0.dist-info/AUTHORS.md
macleod_ide-0.0.2.dev0.dist-info/LICENSE.txt
macleod_ide-0.0.2.dev0.dist-info/METADATA
macleod_ide-0.0.2.dev0.dist-info/WHEEL
macleod_ide-0.0.2.dev0.dist-info/entry_points.txt
macleod_ide-0.0.2.dev0.dist-info/top_level.txt
macleod_ide-0.0.2.dev0.dist-info/RECORD
